django_calendar_hj3415/__init__.py
django_calendar_hj3415/calendar_hj3415/__init__.py
django_calendar_hj3415/calendar_hj3415/admin.py
django_calendar_hj3415/calendar_hj3415/apps.py
django_calendar_hj3415/calendar_hj3415/models.py
django_calendar_hj3415/calendar_hj3415/urls.py
django_calendar_hj3415/calendar_hj3415/utils.py
django_calendar_hj3415/calendar_hj3415/views.py
django_calendar_hj3415/calendar_hj3415/migrations/__init__.py
django_calendar_hj3415/calendar_hj3415/static/calendar_hj3415/calendar.css
django_calendar_hj3415/calendar_hj3415/static/calendar_hj3415/calendar.js
django_calendar_hj3415/calendar_hj3415/templates/calendar_hj3415/_month.html
django_calendar_hj3415/calendar_hj3415/templates/calendar_hj3415/modal.html
django_calendar_hj3415/calendar_hj3415/templatetags/__init__.py
django_calendar_hj3415/calendar_hj3415/templatetags/calendar_tags.py
django_calendar_hj3415-0.0.1.dist-info/WHEEL
django_calendar_hj3415-0.0.1.dist-info/METADATA
django_calendar_hj3415-0.0.1.dist-info/RECORD
